{"ExtraData":null,"Type":0,"Version":"2.1.3","Hashes":{"Files":[{"RelativePath":"AWB.Stream.Emulator.deps.json","Hash":17721605009379803164},{"RelativePath":"AWB.Stream.Emulator.dll","Hash":14156690010193513223},{"RelativePath":"AWB.Stream.Emulator.Interfaces.dll","Hash":3132910582673172166},{"RelativePath":"FileEmulationFramework.Interfaces.dll","Hash":9344872449186471926},{"RelativePath":"FileEmulationFramework.Lib.dll","Hash":75164588319806991},{"RelativePath":"ModConfig.json","Hash":6765325649393254210},{"RelativePath":"Preview.png","Hash":1863136344086842605},{"RelativePath":"Reloaded.Memory.dll","Hash":4221090220205318825},{"RelativePath":"Reloaded.Memory.Sigscan.Definitions.dll","Hash":12553189957395325718},{"RelativePath":"Reloaded.Memory.SigScan.ReloadedII.Interfaces.dll","Hash":13725287046534372337}]},"IgnoreRegexes":[".*\\.json",".*\\.nuspec","AWB\\.Stream\\.Emulator\\.ReleaseMetadata\\.json"],"IncludeRegexes":["ModConfig\\.json","\\.deps\\.json","\\.runtimeconfig\\.json"],"DeltaData":null}